setup.py
codeowl/__init__.py
codeowl/cli.py
codeowl/code.py
codeowl/index.py
codeowl/score.py
codeowl/search.py
codeowl.egg-info/PKG-INFO
codeowl.egg-info/SOURCES.txt
codeowl.egg-info/dependency_links.txt
codeowl.egg-info/entry_points.txt
codeowl.egg-info/requires.txt
codeowl.egg-info/top_level.txt
test/test_code.py
test/test_search.py
test/test_simple_search.py