Metadata-Version: 1.0
Name: codeowl
Version: 0.0.1
Summary: Code Finding Owl
Home-page: UNKNOWN
Author: Florian Ludwig
Author-email: f.ludwig@greyrook.com
License: UNKNOWN
Platform: UNKNOWN
